easy_adb/__init__.py
easy_adb/cli.py
easy_adb/modules/__init__.py
easy_adb/modules/command.py
easy_adb/modules/download.py
easy_adb/modules/server.py
easy_adb/modules/signing.py
easy_adb/resource/__init__.py
easy_adb/resource/adb_terms_conditions.txt
easy_adb-0.1.1.dist-info/LICENSE
easy_adb-0.1.1.dist-info/METADATA
easy_adb-0.1.1.dist-info/WHEEL
easy_adb-0.1.1.dist-info/entry_points.txt
easy_adb-0.1.1.dist-info/top_level.txt
easy_adb-0.1.1.dist-info/RECORD
