Metadata-Version: 2.1
Name: easy-adb
Version: 0.1.1
Summary: Easy to use ADB commands in Python 3
Home-page: https://github.com/minwook-shin/easy-adb
Author: minwook-shin
Author-email: minwook0106@gmail.com
License: LGPLv3
Project-URL: Homepage, https://github.com/minwook-shin/easy-adb
Project-URL: Bug Reports, https://github.com/minwook-shin/easy-adb/issues
Keywords: python,adb,android
Classifier: License :: OSI Approved :: GNU Lesser General Public License v3 (LGPLv3)
Classifier: Development Status :: 4 - Beta
Classifier: Programming Language :: Python :: 3
Requires-Python: >=3.9
License-File: LICENSE
Requires-Dist: requests ==2.31.0
Requires-Dist: adb-shell[usb] ==0.4.4
